yardstiq_compass/__init__.py
yardstiq_compass/compass_provider.py
yardstiq_compass/plugin_loader.py
yardstiq_compass/versions.py
yardstiq_compass/backends/__init__.py
yardstiq_compass/backends/aer_local_backend.py
yardstiq_compass/backends/qsim_local_backend.py
yardstiq_compass/benchmarks/__init__.py
yardstiq_compass/benchmarks/vqe_benchmark.py
yardstiq_local_provider-0.1.0.dist-info/licenses/LICENSE
yardstiq_local_provider-0.1.0.dist-info/METADATA
yardstiq_local_provider-0.1.0.dist-info/WHEEL
yardstiq_local_provider-0.1.0.dist-info/entry_points.txt
yardstiq_local_provider-0.1.0.dist-info/top_level.txt
yardstiq_local_provider-0.1.0.dist-info/RECORD
